holab/__init__.py
holab/losses.py
holab/materials.py
holab/objects.py
holab/physics.py
holab/settings.py
holab/utils.py
holab-0.0.3.dist-info/METADATA
holab-0.0.3.dist-info/WHEEL
holab-0.0.3.dist-info/RECORD
