Metadata-Version: 2.1
Name: holab
Version: 0.0.3
Summary: Acoustic lens design on GPUs with Automatic Differentiation.
License: LGPL-3.0-only
Keywords: jax,acoustics,simulation,hologram,ultrasound
Author: Antonio Stanziola
Author-email: a.stanziola@ucl.ac.uk
Requires-Python: >=3.9,<4.0
Classifier: Environment :: GPU
Classifier: Environment :: GPU :: NVIDIA CUDA
Classifier: Environment :: GPU :: NVIDIA CUDA :: 11.6
Classifier: Environment :: GPU :: NVIDIA CUDA :: 11.7
Classifier: Environment :: GPU :: NVIDIA CUDA :: 11.8
Classifier: Environment :: GPU :: NVIDIA CUDA :: 12 :: 12.0
Classifier: Environment :: GPU :: NVIDIA CUDA :: 12 :: 12.1
Classifier: Intended Audience :: Education
Classifier: Intended Audience :: Science/Research
Classifier: License :: OSI Approved :: GNU Lesser General Public License v3 (LGPLv3)
Classifier: Programming Language :: Python :: 3
Classifier: Programming Language :: Python :: 3.9
Classifier: Programming Language :: Python :: 3.10
Classifier: Programming Language :: Python :: 3.11
Classifier: Programming Language :: Python :: 3.12
Classifier: Programming Language :: Python :: 3.8
Classifier: Topic :: Scientific/Engineering
Classifier: Topic :: Scientific/Engineering :: Physics
Classifier: Topic :: Software Development
Classifier: Topic :: Software Development :: Libraries
Classifier: Topic :: Software Development :: Libraries :: Python Modules
Requires-Dist: jaxtyping (>=0.2.20,<0.3.0)
Requires-Dist: jwave (>=0.1.4,<0.2.0)
Requires-Dist: scikit-image (>=0.21.0,<0.22.0)
Project-URL: Bug Tracker, https://github.com/ucl-bug/holab/issues
Project-URL: Homepage, https://github.com/ucl-bug/holab
Project-URL: Repository, https://github.com/ucl-bug/holab
Project-URL: Support, https://github.com/ucl-bug/holab/issues
